LICENSE
pycommons/lang/__init__.py
pycommons/lang/arrayutils.py
pycommons/lang/booleanutils.py
pycommons/lang/charutils.py
pycommons/lang/exception/__init__.py
pycommons/lang/exception/contexted.py
pycommons/lang/exception/exception.py
pycommons/lang/exception/exceptionutils.py
pycommons/lang/stringutils.py
pycommons/lang/tuple/__init__.py
pycommons/lang/tuple/pair.py
pycommons/lang/tuple/triple.py
pycommons/py.typed
pycommons_lang-0.0.5.dist-info/LICENSE
pycommons_lang-0.0.5.dist-info/METADATA
pycommons_lang-0.0.5.dist-info/WHEEL
pycommons_lang-0.0.5.dist-info/RECORD
