Metadata-Version: 2.1
Name: pycommons-lang
Version: 0.0.5
Summary: Python Commons Lang
Home-page: https://github.com/shashankrnr32/pycommons-lang
License: Apache-2.0
Author: Shashank Sharma
Author-email: shashankrnr32@gmail.com
Requires-Python: >=3.8,<4.0
Classifier: License :: OSI Approved :: Apache Software License
Classifier: Natural Language :: English
Classifier: Programming Language :: Python :: 3
Classifier: Programming Language :: Python :: 3.8
Classifier: Programming Language :: Python :: 3.9
Classifier: Programming Language :: Python :: 3.10
Classifier: Programming Language :: Python :: 3.11
Classifier: Programming Language :: Python :: 3.7
Requires-Dist: importlib_metadata
Requires-Dist: pycommons-base (==0.0.6)
